fastapi_filter_sqlalchemy/__init__.py
fastapi_filter_sqlalchemy/base.py
fastapi_filter_sqlalchemy/constants.py
fastapi_filter_sqlalchemy/filter_sqlalchemy.py
fastapi_filter_sqlalchemy-0.0.5.dist-info/LICENSE
fastapi_filter_sqlalchemy-0.0.5.dist-info/METADATA
fastapi_filter_sqlalchemy-0.0.5.dist-info/WHEEL
fastapi_filter_sqlalchemy-0.0.5.dist-info/RECORD
